api_calls/__init__.py
api_calls/main.py
api_calls-1.0.1.dist-info/METADATA
api_calls-1.0.1.dist-info/WHEEL
api_calls-1.0.1.dist-info/top_level.txt
api_calls-1.0.1.dist-info/RECORD
