Metadata-Version: 2.1
Name: api_calls
Version: 1.0.1
Summary: Package to make api calls
Author-email: Abdulsalam Fawaz <abdulsalamfawaz4@gmail.com>
Project-URL: Homepage, https://github.com/Fawaz441/api-calls
Keywords: api,calls,json,http,api requests,api calls
Classifier: License :: OSI Approved :: MIT License
Classifier: Programming Language :: Python
Classifier: Programming Language :: Python :: 3
Requires-Python: >=3.7
Requires-Dist: requests
